{
  "version": 3,
  "middleware": {
    "/": {
      "files": [
        "server/edge-runtime-webpack.js",
        "server/src/middleware.js"
      ],
      "name": "src/middleware",
      "page": "/",
      "matchers": [
        {
          "regexp": "^(?:\\/(_next\\/data\\/[^/]{1,}))?(?:\\/((?!api|_next|_vercel|.*\\..*).*))(\\.json)?[\\/#\\?]?$",
          "originalSource": "/((?!api|_next|_vercel|.*\\..*).*)"
        }
      ],
      "wasm": [],
      "assets": [],
      "env": {
        "__NEXT_BUILD_ID": "XoA69cYqrHxo9SdtJo5W-",
        "NEXT_SERVER_ACTIONS_ENCRYPTION_KEY": "EKvElLpm31YJ1fiiJT87ZJzwpeMV7pNIClDyStnjVhY=",
        "__NEXT_PREVIEW_MODE_ID": "aeb88f2c590ace5bf1e6b475fdbdca93",
        "__NEXT_PREVIEW_MODE_SIGNING_KEY": "1c51516d5d51740e6c0d2869d41c6747a714ee9ee4f4d6fc2a9d3f13d110d893",
        "__NEXT_PREVIEW_MODE_ENCRYPTION_KEY": "813a1563942d7381bd95ac18dd36639433a24e29904863d992b6fbf40f11e89b"
      }
    }
  },
  "functions": {},
  "sortedMiddleware": [
    "/"
  ]
}